odoo8_addon_travel_journey-8.0.0.1.0-py2.7-nspkg.pth
odoo8_addon_travel_journey-8.0.0.1.0.dist-info/top_level.txt
odoo8_addon_travel_journey-8.0.0.1.0.dist-info/WHEEL
odoo8_addon_travel_journey-8.0.0.1.0.dist-info/RECORD
odoo8_addon_travel_journey-8.0.0.1.0.dist-info/metadata.json
odoo8_addon_travel_journey-8.0.0.1.0.dist-info/DESCRIPTION.rst
odoo8_addon_travel_journey-8.0.0.1.0.dist-info/METADATA
odoo8_addon_travel_journey-8.0.0.1.0.dist-info/namespace_packages.txt
odoo_addons/travel_journey/__openerp__.py
odoo_addons/travel_journey/__init__.py
odoo_addons/travel_journey/README.rst
odoo_addons/travel_journey/security/ir.model.access.csv
odoo_addons/travel_journey/models/travel_journey_class.py
odoo_addons/travel_journey/models/__init__.py
odoo_addons/travel_journey/models/travel_passenger.py
odoo_addons/travel_journey/models/travel_journey_type.py
odoo_addons/travel_journey/models/travel.py
odoo_addons/travel_journey/models/travel_journey.py
odoo_addons/travel_journey/i18n/travel_journey.pot
odoo_addons/travel_journey/i18n/fr.po
odoo_addons/travel_journey/wizard/travel_journey_import.py
odoo_addons/travel_journey/wizard/travel_journey_import_view.xml
odoo_addons/travel_journey/wizard/__init__.py
odoo_addons/travel_journey/wizard/travel_summary.py
odoo_addons/travel_journey/wizard/travel_summary_view.xml
odoo_addons/travel_journey/views/travel_view.xml
odoo_addons/travel_journey/views/travel_journey_view.xml
odoo_addons/travel_journey/views/travel_passenger_view.xml
odoo_addons/travel_journey/data/travel_journey_data.xml
odoo_addons/travel_journey/tests/__init__.py
odoo_addons/travel_journey/tests/test_journey.py
